[
  {
    "question_id": "NCERT-EXEMPLAR-M7-CH3-Q1",
    "board": "NCERT",
    "class_level": 7,
    "subject": "Mathematics",
    "book": "Exemplar Problems - Mathematics",
    "chapter_number": 3,
    "chapter_title": "Data Handling",
    "language": "English",
    "source_kind": "EXEMPLAR",
    "question_type": "MCQ",
    "question_text": "Let x, y, z be three observations. The mean of these observations is",
    "options": [
      "(x × y × z) / 3",
      "(x + y + z) / 3",
      "(x - y - z) / 3",
      "(x × y + z) / 3"
    ],
    "answer_key": "(x + y + z) / 3",
    "answer_explanation": "Mean is the sum of observations divided by the number of observations.",
    "difficulty": "easy",
    "blooms_level": "remember",
    "source_file": "gemp103.pdf",
    "source_pages": [
      72
    ],
    "provenance_excerpt": "Let x, y, z be three observations. The mean of these observations is",
    "review_state": "approved",
    "qa_flags": []
  },
  {
    "question_id": "NCERT-EXEMPLAR-M7-CH3-Q2",
    "board": "NCERT",
    "class_level": 7,
    "subject": "Mathematics",
    "book": "Exemplar Problems - Mathematics",
    "chapter_number": 3,
    "chapter_title": "Data Handling",
    "language": "English",
    "source_kind": "EXEMPLAR",
    "question_type": "MCQ",
    "question_text": "The number of trees in different parks of a city are 33, 38, 48, 33, 34, 34, 33 and 24. The mode of this data is",
    "options": [
      "24",
      "34",
      "33",
      "48"
    ],
    "answer_key": "33",
    "answer_explanation": "33 occurs the most number of times (3 times).",
    "difficulty": "easy",
    "blooms_level": "apply",
    "source_file": "gemp103.pdf",
    "source_pages": [
      72
    ],
    "provenance_excerpt": "The number of trees in different parks of a city are 33, 38, 48, 33, 34, 34, 33 and 24. The mode of this data is",
    "review_state": "approved",
    "qa_flags": []
  },
  {
    "question_id": "NCERT-EXEMPLAR-M7-CH3-Q3",
    "board": "NCERT",
    "class_level": 7,
    "subject": "Mathematics",
    "book": "Exemplar Problems - Mathematics",
    "chapter_number": 3,
    "chapter_title": "Data Handling",
    "language": "English",
    "source_kind": "EXEMPLAR",
    "question_type": "MCQ",
    "question_text": "Which measures of central tendency get affected if the extreme observations on both the ends of a data arranged in descending order are removed?",
    "options": [
      "Mean and mode",
      "Mean and Median",
      "Mode and Median",
      "Mean, Median and Mode"
    ],
    "answer_key": "Mean and mode",
    "answer_explanation": "Median remains unaffected when an equal number of extreme values are removed.",
    "difficulty": "medium",
    "blooms_level": "understand",
    "source_file": "gemp103.pdf",
    "source_pages": [
      72
    ],
    "provenance_excerpt": "Which measures of central tendency get affected if the extreme observations on both the ends of a data arranged in desce",
    "review_state": "approved",
    "qa_flags": []
  },
  {
    "question_id": "NCERT-EXEMPLAR-M7-CH3-Q4",
    "board": "NCERT",
    "class_level": 7,
    "subject": "Mathematics",
    "book": "Exemplar Problems - Mathematics",
    "chapter_number": 3,
    "chapter_title": "Data Handling",
    "language": "English",
    "source_kind": "EXEMPLAR",
    "question_type": "MCQ",
    "question_text": "The range of the data : 21, 6, 17, 18, 12, 8, 4, 13 is",
    "options": [
      "17",
      "12",
      "8",
      "15"
    ],
    "answer_key": "17",
    "answer_explanation": "Highest = 21, Lowest = 4. Range = 21 - 4 = 17.",
    "difficulty": "easy",
    "blooms_level": "apply",
    "source_file": "gemp103.pdf",
    "source_pages": [
      72
    ],
    "provenance_excerpt": "The range of the data : 21, 6, 17, 18, 12, 8, 4, 13 is",
    "review_state": "approved",
    "qa_flags": []
  },
  {
    "question_id": "NCERT-EXEMPLAR-M7-CH3-Q5",
    "board": "NCERT",
    "class_level": 7,
    "subject": "Mathematics",
    "book": "Exemplar Problems - Mathematics",
    "chapter_number": 3,
    "chapter_title": "Data Handling",
    "language": "English",
    "source_kind": "EXEMPLAR",
    "question_type": "MCQ",
    "question_text": "The median of the data : 3, 4, 5, 6, 7, 3, 4 is",
    "options": [
      "5",
      "3",
      "4",
      "6"
    ],
    "answer_key": "4",
    "answer_explanation": "Arranging: 3, 3, 4, 4, 5, 6, 7. Middle term is the 4th term, which is 4.",
    "difficulty": "easy",
    "blooms_level": "apply",
    "source_file": "gemp103.pdf",
    "source_pages": [
      72
    ],
    "provenance_excerpt": "The median of the data : 3, 4, 5, 6, 7, 3, 4 is",
    "review_state": "approved",
    "qa_flags": []
  },
  {
    "question_id": "NCERT-EXEMPLAR-M7-CH3-Q6",
    "board": "NCERT",
    "class_level": 7,
    "subject": "Mathematics",
    "book": "Exemplar Problems - Mathematics",
    "chapter_number": 3,
    "chapter_title": "Data Handling",
    "language": "English",
    "source_kind": "EXEMPLAR",
    "question_type": "MCQ",
    "question_text": "Out of 5 brands of chocolates in a shop, a boy has to purchase the brand which is most liked by children. What measure of central tendency would be most appropriate if the data is provided to him?",
    "options": [
      "Mean",
      "Mode",
      "Median",
      "Any of the three"
    ],
    "answer_key": "Mode",
    "answer_explanation": "Mode helps to find the most preferred or 'most liked' item.",
    "difficulty": "medium",
    "blooms_level": "understand",
    "source_file": "gemp103.pdf",
    "source_pages": [
      72
    ],
    "provenance_excerpt": "Out of 5 brands of chocolates in a shop, a boy has to purchase the brand which is most liked by children. What measure o",
    "review_state": "approved",
    "qa_flags": []
  },
  {
    "question_id": "NCERT-EXEMPLAR-M7-CH3-Q7",
    "board": "NCERT",
    "class_level": 7,
    "subject": "Mathematics",
    "book": "Exemplar Problems - Mathematics",
    "chapter_number": 3,
    "chapter_title": "Data Handling",
    "language": "English",
    "source_kind": "EXEMPLAR",
    "question_type": "MCQ",
    "question_text": "There are 2 aces in each of the given set of cards placed face down. From which set are you certain to pick the two aces in the first go?",
    "options": [
      "(a)",
      "(b)",
      "(c)",
      "(d)"
    ],
    "answer_key": "(c)",
    "answer_explanation": "The set which has only 2 cards (both aces) gives certainty.",
    "difficulty": "easy",
    "blooms_level": "apply",
    "source_file": "gemp103.pdf",
    "source_pages": [
      72
    ],
    "provenance_excerpt": "There are 2 aces in each of the given set of cards placed face down. From which set are you certain to pick the two aces",
    "review_state": "approved",
    "qa_flags": []
  },
  {
    "question_id": "NCERT-EXEMPLAR-M7-CH3-Q8",
    "board": "NCERT",
    "class_level": 7,
    "subject": "Mathematics",
    "book": "Exemplar Problems - Mathematics",
    "chapter_number": 3,
    "chapter_title": "Data Handling",
    "language": "English",
    "source_kind": "EXEMPLAR",
    "question_type": "MCQ",
    "question_text": "In the previous question, what is the probability of picking up an ace from set (d)?",
    "options": [
      "1/6",
      "2/6",
      "3/6",
      "4/6"
    ],
    "answer_key": "2/6",
    "answer_explanation": "Set (d) has 6 cards. 2 are aces. Probability = 2/6.",
    "difficulty": "easy",
    "blooms_level": "apply",
    "source_file": "gemp103.pdf",
    "source_pages": [
      73
    ],
    "provenance_excerpt": "In the previous question, what is the probability of picking up an ace from set (d)?",
    "review_state": "approved",
    "qa_flags": []
  },
  {
    "question_id": "NCERT-EXEMPLAR-M7-CH3-Q9",
    "board": "NCERT",
    "class_level": 7,
    "subject": "Mathematics",
    "book": "Exemplar Problems - Mathematics",
    "chapter_number": 3,
    "chapter_title": "Data Handling",
    "language": "English",
    "source_kind": "EXEMPLAR",
    "question_type": "MCQ",
    "question_text": "The difference between the highest and the lowest observations in a data is its",
    "options": [
      "frequency",
      "width",
      "range",
      "mode"
    ],
    "answer_key": "range",
    "answer_explanation": "Range = Highest - Lowest.",
    "difficulty": "easy",
    "blooms_level": "remember",
    "source_file": "gemp103.pdf",
    "source_pages": [
      73
    ],
    "provenance_excerpt": "The difference between the highest and the lowest observations in a data is its",
    "review_state": "approved",
    "qa_flags": []
  },
  {
    "question_id": "NCERT-EXEMPLAR-M7-CH3-Q10",
    "board": "NCERT",
    "class_level": 7,
    "subject": "Mathematics",
    "book": "Exemplar Problems - Mathematics",
    "chapter_number": 3,
    "chapter_title": "Data Handling",
    "language": "English",
    "source_kind": "EXEMPLAR",
    "question_type": "MCQ",
    "question_text": "In a school, only 2 out of 5 students can participate in a quiz. What is the chance that a student picked at random makes it to the competition?",
    "options": [
      "20%",
      "40%",
      "50%",
      "30%"
    ],
    "answer_key": "40%",
    "answer_explanation": "2/5 = 40%.",
    "difficulty": "medium",
    "blooms_level": "apply",
    "source_file": "gemp103.pdf",
    "source_pages": [
      73
    ],
    "provenance_excerpt": "In a school, only 2 out of 5 students can participate in a quiz. What is the chance that a student picked at random make",
    "review_state": "approved",
    "qa_flags": []
  },
  {
    "question_id": "NCERT-EXEMPLAR-M7-CH3-Q11",
    "board": "NCERT",
    "class_level": 7,
    "subject": "Mathematics",
    "book": "Exemplar Problems - Mathematics",
    "chapter_number": 3,
    "chapter_title": "Data Handling",
    "language": "English",
    "source_kind": "EXEMPLAR",
    "question_type": "MCQ",
    "question_text": "Some integers are marked on a board: 15, -16, 21. What is the range of these integers?",
    "options": [
      "31",
      "37",
      "20",
      "3"
    ],
    "answer_key": "37",
    "answer_explanation": "Highest = 21. Lowest = -16. Range = 21 - (-16) = 37.",
    "difficulty": "medium",
    "blooms_level": "apply",
    "source_file": "gemp103.pdf",
    "source_pages": [
      73
    ],
    "provenance_excerpt": "Some integers are marked on a board: 15, -16, 21. What is the range of these integers?",
    "review_state": "approved",
    "qa_flags": []
  },
  {
    "question_id": "NCERT-EXEMPLAR-M7-CH3-Q12",
    "board": "NCERT",
    "class_level": 7,
    "subject": "Mathematics",
    "book": "Exemplar Problems - Mathematics",
    "chapter_number": 3,
    "chapter_title": "Data Handling",
    "language": "English",
    "source_kind": "EXEMPLAR",
    "question_type": "MCQ",
    "question_text": "On tossing a coin, the outcome is",
    "options": [
      "only head",
      "only tail",
      "neither head nor tail",
      "either head or tail"
    ],
    "answer_key": "either head or tail",
    "answer_explanation": "Coin toss has two possible outcomes.",
    "difficulty": "easy",
    "blooms_level": "understand",
    "source_file": "gemp103.pdf",
    "source_pages": [
      73
    ],
    "provenance_excerpt": "On tossing a coin, the outcome is",
    "review_state": "approved",
    "qa_flags": []
  },
  {
    "question_id": "NCERT-EXEMPLAR-M7-CH3-Q13",
    "board": "NCERT",
    "class_level": 7,
    "subject": "Mathematics",
    "book": "Exemplar Problems - Mathematics",
    "chapter_number": 3,
    "chapter_title": "Data Handling",
    "language": "English",
    "source_kind": "EXEMPLAR",
    "question_type": "MCQ",
    "question_text": "The mean of three numbers is 40. All the three numbers are different natural numbers. If lowest is 19, what could be highest possible number of remaining two numbers?",
    "options": [
      "81",
      "40",
      "100",
      "71"
    ],
    "answer_key": "81",
    "answer_explanation": "Sum = 120. If lowest is 19, next lowest different natural number must be >19, i.e., 20. Then highest = 120 - (19+20) = 81.",
    "difficulty": "hard",
    "blooms_level": "apply",
    "source_file": "gemp103.pdf",
    "source_pages": [
      73
    ],
    "provenance_excerpt": "The mean of three numbers is 40. All the three numbers are different natural numbers. If lowest is 19, what could be hig",
    "review_state": "approved",
    "qa_flags": []
  },
  {
    "question_id": "NCERT-EXEMPLAR-M7-CH3-Q14",
    "board": "NCERT",
    "class_level": 7,
    "subject": "Mathematics",
    "book": "Exemplar Problems - Mathematics",
    "chapter_number": 3,
    "chapter_title": "Data Handling",
    "language": "English",
    "source_kind": "EXEMPLAR",
    "question_type": "MCQ",
    "question_text": "Khilona earned scores of 97, 73 and 88 respectively in her first three examinations. If she scored 80 in the fourth examination, then her average score will be",
    "options": [
      "increased by 1",
      "increased by 1.5",
      "decreased by 1",
      "decreased by 1.5"
    ],
    "answer_key": "decreased by 1.5",
    "answer_explanation": "Average of 3 = (97+73+88)/3 = 258/3 = 86. Average of 4 = (258+80)/4 = 338/4 = 84.5. It decreased by 1.5.",
    "difficulty": "medium",
    "blooms_level": "apply",
    "source_file": "gemp103.pdf",
    "source_pages": [
      73
    ],
    "provenance_excerpt": "Khilona earned scores of 97, 73 and 88 respectively in her first three examinations. If she scored 80 in the fourth exam",
    "review_state": "approved",
    "qa_flags": []
  },
  {
    "question_id": "NCERT-EXEMPLAR-M7-CH3-Q15",
    "board": "NCERT",
    "class_level": 7,
    "subject": "Mathematics",
    "book": "Exemplar Problems - Mathematics",
    "chapter_number": 3,
    "chapter_title": "Data Handling",
    "language": "English",
    "source_kind": "EXEMPLAR",
    "question_type": "MCQ",
    "question_text": "Which measure of central tendency best represents the data of the most popular politician after a debate?",
    "options": [
      "Mean",
      "Median",
      "Mode",
      "Any of the above"
    ],
    "answer_key": "Mode",
    "answer_explanation": "Most popular means highest frequency.",
    "difficulty": "easy",
    "blooms_level": "understand",
    "source_file": "gemp103.pdf",
    "source_pages": [
      73
    ],
    "provenance_excerpt": "Which measure of central tendency best represents the data of the most popular politician after a debate?",
    "review_state": "approved",
    "qa_flags": []
  },
  {
    "question_id": "NCERT-EXEMPLAR-M7-CH3-Q16",
    "board": "NCERT",
    "class_level": 7,
    "subject": "Mathematics",
    "book": "Exemplar Problems - Mathematics",
    "chapter_number": 3,
    "chapter_title": "Data Handling",
    "language": "English",
    "source_kind": "EXEMPLAR",
    "question_type": "MCQ",
    "question_text": "Which of the following has the same mean, median and mode?",
    "options": [
      "6, 2, 5, 4, 3, 4, 1",
      "4, 2, 2, 1, 3, 2, 3",
      "2, 3, 7, 3, 8, 3, 2",
      "4, 3, 4, 3, 4, 6, 4"
    ],
    "answer_key": "4, 3, 4, 3, 4, 6, 4",
    "answer_explanation": "Mean of 4,3,4,3,4,6,4 is 28/7=4. Median is 4. Mode is 4. They are the same.",
    "difficulty": "medium",
    "blooms_level": "apply",
    "source_file": "gemp103.pdf",
    "source_pages": [
      74
    ],
    "provenance_excerpt": "Which of the following has the same mean, median and mode?",
    "review_state": "approved",
    "qa_flags": []
  },
  {
    "question_id": "NCERT-EXEMPLAR-M7-CH3-Q17",
    "board": "NCERT",
    "class_level": 7,
    "subject": "Mathematics",
    "book": "Exemplar Problems - Mathematics",
    "chapter_number": 3,
    "chapter_title": "Data Handling",
    "language": "English",
    "source_kind": "EXEMPLAR",
    "question_type": "Fill in the Blanks",
    "question_text": "The difference between the highest and the lowest observations of a data is called _________.",
    "options": [],
    "answer_key": "range",
    "answer_explanation": "Range is defined as highest - lowest.",
    "difficulty": "easy",
    "blooms_level": "remember",
    "source_file": "gemp103.pdf",
    "source_pages": [
      74,
      75
    ],
    "provenance_excerpt": "The difference between the highest and the lowest observations of a data is called _________.",
    "review_state": "approved",
    "qa_flags": []
  },
  {
    "question_id": "NCERT-EXEMPLAR-M7-CH3-Q18",
    "board": "NCERT",
    "class_level": 7,
    "subject": "Mathematics",
    "book": "Exemplar Problems - Mathematics",
    "chapter_number": 3,
    "chapter_title": "Data Handling",
    "language": "English",
    "source_kind": "EXEMPLAR",
    "question_type": "Fill in the Blanks",
    "question_text": "The mean of a data is defined as _________.",
    "options": [],
    "answer_key": "(sum of all observations) / (number of observations)",
    "answer_explanation": "Formula for mean.",
    "difficulty": "easy",
    "blooms_level": "remember",
    "source_file": "gemp103.pdf",
    "source_pages": [
      74,
      75
    ],
    "provenance_excerpt": "The mean of a data is defined as _________.",
    "review_state": "approved",
    "qa_flags": []
  },
  {
    "question_id": "NCERT-EXEMPLAR-M7-CH3-Q19",
    "board": "NCERT",
    "class_level": 7,
    "subject": "Mathematics",
    "book": "Exemplar Problems - Mathematics",
    "chapter_number": 3,
    "chapter_title": "Data Handling",
    "language": "English",
    "source_kind": "EXEMPLAR",
    "question_type": "Fill in the Blanks",
    "question_text": "In a set of observations, the observation that occurs the most often is called _________.",
    "options": [],
    "answer_key": "mode",
    "answer_explanation": "Definition of mode.",
    "difficulty": "easy",
    "blooms_level": "remember",
    "source_file": "gemp103.pdf",
    "source_pages": [
      74,
      75
    ],
    "provenance_excerpt": "In a set of observations, the observation that occurs the most often is called _________.",
    "review_state": "approved",
    "qa_flags": []
  },
  {
    "question_id": "NCERT-EXEMPLAR-M7-CH3-Q20",
    "board": "NCERT",
    "class_level": 7,
    "subject": "Mathematics",
    "book": "Exemplar Problems - Mathematics",
    "chapter_number": 3,
    "chapter_title": "Data Handling",
    "language": "English",
    "source_kind": "EXEMPLAR",
    "question_type": "Fill in the Blanks",
    "question_text": "In a given data, arranged in ascending or descending order, the middle most observation is called _________.",
    "options": [],
    "answer_key": "median",
    "answer_explanation": "Definition of median.",
    "difficulty": "easy",
    "blooms_level": "remember",
    "source_file": "gemp103.pdf",
    "source_pages": [
      74,
      75
    ],
    "provenance_excerpt": "In a given data, arranged in ascending or descending order, the middle most observation is called _________.",
    "review_state": "approved",
    "qa_flags": []
  },
  {
    "question_id": "NCERT-EXEMPLAR-M7-CH3-Q21",
    "board": "NCERT",
    "class_level": 7,
    "subject": "Mathematics",
    "book": "Exemplar Problems - Mathematics",
    "chapter_number": 3,
    "chapter_title": "Data Handling",
    "language": "English",
    "source_kind": "EXEMPLAR",
    "question_type": "Fill in the Blanks",
    "question_text": "Mean, Median, Mode are the measures of _________.",
    "options": [],
    "answer_key": "central tendency",
    "answer_explanation": "Standard terminology.",
    "difficulty": "easy",
    "blooms_level": "remember",
    "source_file": "gemp103.pdf",
    "source_pages": [
      74,
      75
    ],
    "provenance_excerpt": "Mean, Median, Mode are the measures of _________.",
    "review_state": "approved",
    "qa_flags": []
  },
  {
    "question_id": "NCERT-EXEMPLAR-M7-CH3-Q22",
    "board": "NCERT",
    "class_level": 7,
    "subject": "Mathematics",
    "book": "Exemplar Problems - Mathematics",
    "chapter_number": 3,
    "chapter_title": "Data Handling",
    "language": "English",
    "source_kind": "EXEMPLAR",
    "question_type": "Fill in the Blanks",
    "question_text": "The probability of an event which is certain to happen is _________.",
    "options": [],
    "answer_key": "1",
    "answer_explanation": "Certain event probability.",
    "difficulty": "easy",
    "blooms_level": "remember",
    "source_file": "gemp103.pdf",
    "source_pages": [
      74,
      75
    ],
    "provenance_excerpt": "The probability of an event which is certain to happen is _________.",
    "review_state": "approved",
    "qa_flags": []
  },
  {
    "question_id": "NCERT-EXEMPLAR-M7-CH3-Q23",
    "board": "NCERT",
    "class_level": 7,
    "subject": "Mathematics",
    "book": "Exemplar Problems - Mathematics",
    "chapter_number": 3,
    "chapter_title": "Data Handling",
    "language": "English",
    "source_kind": "EXEMPLAR",
    "question_type": "Fill in the Blanks",
    "question_text": "The probability of an event which is impossible to happen is _________.",
    "options": [],
    "answer_key": "0",
    "answer_explanation": "Impossible event probability.",
    "difficulty": "easy",
    "blooms_level": "remember",
    "source_file": "gemp103.pdf",
    "source_pages": [
      74,
      75
    ],
    "provenance_excerpt": "The probability of an event which is impossible to happen is _________.",
    "review_state": "approved",
    "qa_flags": []
  },
  {
    "question_id": "NCERT-EXEMPLAR-M7-CH3-Q24",
    "board": "NCERT",
    "class_level": 7,
    "subject": "Mathematics",
    "book": "Exemplar Problems - Mathematics",
    "chapter_number": 3,
    "chapter_title": "Data Handling",
    "language": "English",
    "source_kind": "EXEMPLAR",
    "question_type": "Fill in the Blanks",
    "question_text": "When a die is thrown, the probability of getting a number less than 7 is _________.",
    "options": [],
    "answer_key": "1",
    "answer_explanation": "All outcomes (1-6) are less than 7. Hence probability is 6/6 = 1.",
    "difficulty": "easy",
    "blooms_level": "remember",
    "source_file": "gemp103.pdf",
    "source_pages": [
      74,
      75
    ],
    "provenance_excerpt": "When a die is thrown, the probability of getting a number less than 7 is _________.",
    "review_state": "approved",
    "qa_flags": []
  },
  {
    "question_id": "NCERT-EXEMPLAR-M7-CH3-Q25",
    "board": "NCERT",
    "class_level": 7,
    "subject": "Mathematics",
    "book": "Exemplar Problems - Mathematics",
    "chapter_number": 3,
    "chapter_title": "Data Handling",
    "language": "English",
    "source_kind": "EXEMPLAR",
    "question_type": "Fill in the Blanks",
    "question_text": "In Throwing a die the number of possible outcomes is _________.",
    "options": [],
    "answer_key": "6",
    "answer_explanation": "Outcomes are 1, 2, 3, 4, 5, 6.",
    "difficulty": "easy",
    "blooms_level": "remember",
    "source_file": "gemp103.pdf",
    "source_pages": [
      74,
      75
    ],
    "provenance_excerpt": "In Throwing a die the number of possible outcomes is _________.",
    "review_state": "approved",
    "qa_flags": []
  },
  {
    "question_id": "NCERT-EXEMPLAR-M7-CH3-Q26",
    "board": "NCERT",
    "class_level": 7,
    "subject": "Mathematics",
    "book": "Exemplar Problems - Mathematics",
    "chapter_number": 3,
    "chapter_title": "Data Handling",
    "language": "English",
    "source_kind": "EXEMPLAR",
    "question_type": "Fill in the Blanks",
    "question_text": "_________ can be used to compare two collections of data.",
    "options": [],
    "answer_key": "Double bar graph",
    "answer_explanation": "Used for comparing two data collections.",
    "difficulty": "easy",
    "blooms_level": "remember",
    "source_file": "gemp103.pdf",
    "source_pages": [
      74,
      75
    ],
    "provenance_excerpt": "_________ can be used to compare two collections of data.",
    "review_state": "approved",
    "qa_flags": []
  },
  {
    "question_id": "NCERT-EXEMPLAR-M7-CH3-Q27",
    "board": "NCERT",
    "class_level": 7,
    "subject": "Mathematics",
    "book": "Exemplar Problems - Mathematics",
    "chapter_number": 3,
    "chapter_title": "Data Handling",
    "language": "English",
    "source_kind": "EXEMPLAR",
    "question_type": "Fill in the Blanks",
    "question_text": "The representation of data with bars of uniform width is called _________.",
    "options": [],
    "answer_key": "bar graph",
    "answer_explanation": "Definition of bar graph.",
    "difficulty": "easy",
    "blooms_level": "remember",
    "source_file": "gemp103.pdf",
    "source_pages": [
      74,
      75
    ],
    "provenance_excerpt": "The representation of data with bars of uniform width is called _________.",
    "review_state": "approved",
    "qa_flags": []
  },
  {
    "question_id": "NCERT-EXEMPLAR-M7-CH3-Q28",
    "board": "NCERT",
    "class_level": 7,
    "subject": "Mathematics",
    "book": "Exemplar Problems - Mathematics",
    "chapter_number": 3,
    "chapter_title": "Data Handling",
    "language": "English",
    "source_kind": "EXEMPLAR",
    "question_type": "Fill in the Blanks",
    "question_text": "If the arithmetic mean of 8, 4, x, 6, 2, 7 is 5, then the value of x is _________.",
    "options": [],
    "answer_key": "3",
    "answer_explanation": "Sum = 27 + x. (27+x)/6 = 5 => 27+x = 30 => x = 3.",
    "difficulty": "medium",
    "blooms_level": "apply",
    "source_file": "gemp103.pdf",
    "source_pages": [
      74,
      75
    ],
    "provenance_excerpt": "If the arithmetic mean of 8, 4, x, 6, 2, 7 is 5, then the value of x is _________.",
    "review_state": "approved",
    "qa_flags": []
  },
  {
    "question_id": "NCERT-EXEMPLAR-M7-CH3-Q29",
    "board": "NCERT",
    "class_level": 7,
    "subject": "Mathematics",
    "book": "Exemplar Problems - Mathematics",
    "chapter_number": 3,
    "chapter_title": "Data Handling",
    "language": "English",
    "source_kind": "EXEMPLAR",
    "question_type": "Fill in the Blanks",
    "question_text": "The median of any data lies between the _________ and _________ observations.",
    "options": [],
    "answer_key": "lowest, highest",
    "answer_explanation": "Median is a central value.",
    "difficulty": "medium",
    "blooms_level": "apply",
    "source_file": "gemp103.pdf",
    "source_pages": [
      74,
      75
    ],
    "provenance_excerpt": "The median of any data lies between the _________ and _________ observations.",
    "review_state": "approved",
    "qa_flags": []
  },
  {
    "question_id": "NCERT-EXEMPLAR-M7-CH3-Q30",
    "board": "NCERT",
    "class_level": 7,
    "subject": "Mathematics",
    "book": "Exemplar Problems - Mathematics",
    "chapter_number": 3,
    "chapter_title": "Data Handling",
    "language": "English",
    "source_kind": "EXEMPLAR",
    "question_type": "Fill in the Blanks",
    "question_text": "Median is one of the observations in the data if number of observations is _________.",
    "options": [],
    "answer_key": "odd",
    "answer_explanation": "If odd, it is exactly the middle observation.",
    "difficulty": "easy",
    "blooms_level": "remember",
    "source_file": "gemp103.pdf",
    "source_pages": [
      74,
      75
    ],
    "provenance_excerpt": "Median is one of the observations in the data if number of observations is _________.",
    "review_state": "approved",
    "qa_flags": []
  },
  {
    "question_id": "NCERT-EXEMPLAR-M7-CH3-Q31",
    "board": "NCERT",
    "class_level": 7,
    "subject": "Mathematics",
    "book": "Exemplar Problems - Mathematics",
    "chapter_number": 3,
    "chapter_title": "Data Handling",
    "language": "English",
    "source_kind": "EXEMPLAR",
    "question_type": "Fill in the Blanks",
    "question_text": "The probability of selection of the student is highest whose weight is in the interval _________.",
    "options": [],
    "answer_key": "52 - 55",
    "answer_explanation": "52-55 has highest frequency (25 students).",
    "difficulty": "easy",
    "blooms_level": "remember",
    "source_file": "gemp103.pdf",
    "source_pages": [
      74,
      75
    ],
    "provenance_excerpt": "The probability of selection of the student is highest whose weight is in the interval _________.",
    "review_state": "approved",
    "qa_flags": []
  },
  {
    "question_id": "NCERT-EXEMPLAR-M7-CH3-Q32",
    "board": "NCERT",
    "class_level": 7,
    "subject": "Mathematics",
    "book": "Exemplar Problems - Mathematics",
    "chapter_number": 3,
    "chapter_title": "Data Handling",
    "language": "English",
    "source_kind": "EXEMPLAR",
    "question_type": "True/False",
    "question_text": "If a die is thrown, the probability of getting a number greater than 6 is 1.",
    "options": [
      "True",
      "False"
    ],
    "answer_key": "False",
    "answer_explanation": "It is 0, since no number >6 on a standard die.",
    "difficulty": "easy",
    "blooms_level": "understand",
    "source_file": "gemp103.pdf",
    "source_pages": [
      75,
      76
    ],
    "provenance_excerpt": "If a die is thrown, the probability of getting a number greater than 6 is 1.",
    "review_state": "approved",
    "qa_flags": []
  },
  {
    "question_id": "NCERT-EXEMPLAR-M7-CH3-Q33",
    "board": "NCERT",
    "class_level": 7,
    "subject": "Mathematics",
    "book": "Exemplar Problems - Mathematics",
    "chapter_number": 3,
    "chapter_title": "Data Handling",
    "language": "English",
    "source_kind": "EXEMPLAR",
    "question_type": "True/False",
    "question_text": "When a coin is tossed, there are 2 possible outcomes.",
    "options": [
      "True",
      "False"
    ],
    "answer_key": "True",
    "answer_explanation": "Head and tail.",
    "difficulty": "easy",
    "blooms_level": "understand",
    "source_file": "gemp103.pdf",
    "source_pages": [
      75,
      76
    ],
    "provenance_excerpt": "When a coin is tossed, there are 2 possible outcomes.",
    "review_state": "approved",
    "qa_flags": []
  },
  {
    "question_id": "NCERT-EXEMPLAR-M7-CH3-Q34",
    "board": "NCERT",
    "class_level": 7,
    "subject": "Mathematics",
    "book": "Exemplar Problems - Mathematics",
    "chapter_number": 3,
    "chapter_title": "Data Handling",
    "language": "English",
    "source_kind": "EXEMPLAR",
    "question_type": "True/False",
    "question_text": "If the extreme observations on both the ends of a data arranged in ascending order are removed, the median gets affected.",
    "options": [
      "True",
      "False"
    ],
    "answer_key": "False",
    "answer_explanation": "Median is unchanged.",
    "difficulty": "medium",
    "blooms_level": "understand",
    "source_file": "gemp103.pdf",
    "source_pages": [
      75,
      76
    ],
    "provenance_excerpt": "If the extreme observations on both the ends of a data arranged in ascending order are removed, the median gets affected",
    "review_state": "approved",
    "qa_flags": []
  },
  {
    "question_id": "NCERT-EXEMPLAR-M7-CH3-Q35",
    "board": "NCERT",
    "class_level": 7,
    "subject": "Mathematics",
    "book": "Exemplar Problems - Mathematics",
    "chapter_number": 3,
    "chapter_title": "Data Handling",
    "language": "English",
    "source_kind": "EXEMPLAR",
    "question_type": "True/False",
    "question_text": "The measures of central tendency may not lie between the maximum and minimum values of data.",
    "options": [
      "True",
      "False"
    ],
    "answer_key": "False",
    "answer_explanation": "They always lie between min and max.",
    "difficulty": "medium",
    "blooms_level": "understand",
    "source_file": "gemp103.pdf",
    "source_pages": [
      75,
      76
    ],
    "provenance_excerpt": "The measures of central tendency may not lie between the maximum and minimum values of data.",
    "review_state": "approved",
    "qa_flags": []
  },
  {
    "question_id": "NCERT-EXEMPLAR-M7-CH3-Q36",
    "board": "NCERT",
    "class_level": 7,
    "subject": "Mathematics",
    "book": "Exemplar Problems - Mathematics",
    "chapter_number": 3,
    "chapter_title": "Data Handling",
    "language": "English",
    "source_kind": "EXEMPLAR",
    "question_type": "True/False",
    "question_text": "It is impossible to get a sum of 14 of the numbers on both dice when a pair of dice is thrown together.",
    "options": [
      "True",
      "False"
    ],
    "answer_key": "True",
    "answer_explanation": "Max sum is 6+6 = 12.",
    "difficulty": "easy",
    "blooms_level": "understand",
    "source_file": "gemp103.pdf",
    "source_pages": [
      75,
      76
    ],
    "provenance_excerpt": "It is impossible to get a sum of 14 of the numbers on both dice when a pair of dice is thrown together.",
    "review_state": "approved",
    "qa_flags": []
  },
  {
    "question_id": "NCERT-EXEMPLAR-M7-CH3-Q37",
    "board": "NCERT",
    "class_level": 7,
    "subject": "Mathematics",
    "book": "Exemplar Problems - Mathematics",
    "chapter_number": 3,
    "chapter_title": "Data Handling",
    "language": "English",
    "source_kind": "EXEMPLAR",
    "question_type": "True/False",
    "question_text": "The probability of the spinning arrow stopping in the shaded region (Fig. 3.4) is 1/2.",
    "options": [
      "True",
      "False"
    ],
    "answer_key": "True",
    "answer_explanation": "If exactly half area is shaded.",
    "difficulty": "easy",
    "blooms_level": "understand",
    "source_file": "gemp103.pdf",
    "source_pages": [
      75,
      76
    ],
    "provenance_excerpt": "The probability of the spinning arrow stopping in the shaded region (Fig. 3.4) is 1/2.",
    "review_state": "approved",
    "qa_flags": []
  },
  {
    "question_id": "NCERT-EXEMPLAR-M7-CH3-Q38",
    "board": "NCERT",
    "class_level": 7,
    "subject": "Mathematics",
    "book": "Exemplar Problems - Mathematics",
    "chapter_number": 3,
    "chapter_title": "Data Handling",
    "language": "English",
    "source_kind": "EXEMPLAR",
    "question_type": "True/False",
    "question_text": "A coin is tossed 15 times and outcomes are ... The chance of occurence of a head is 50 per cent.",
    "options": [
      "True",
      "False"
    ],
    "answer_key": "False",
    "answer_explanation": "Chance depends only on theoretical probability unless referring to experimental, but here there are 6 heads out of 15, which is 40%.",
    "difficulty": "medium",
    "blooms_level": "understand",
    "source_file": "gemp103.pdf",
    "source_pages": [
      75,
      76
    ],
    "provenance_excerpt": "A coin is tossed 15 times and outcomes are ... The chance of occurence of a head is 50 per cent.",
    "review_state": "approved",
    "qa_flags": []
  },
  {
    "question_id": "NCERT-EXEMPLAR-M7-CH3-Q39",
    "board": "NCERT",
    "class_level": 7,
    "subject": "Mathematics",
    "book": "Exemplar Problems - Mathematics",
    "chapter_number": 3,
    "chapter_title": "Data Handling",
    "language": "English",
    "source_kind": "EXEMPLAR",
    "question_type": "True/False",
    "question_text": "Mean, Median and Mode may be the same for some data.",
    "options": [
      "True",
      "False"
    ],
    "answer_key": "True",
    "answer_explanation": "Yes, they can be equal.",
    "difficulty": "easy",
    "blooms_level": "understand",
    "source_file": "gemp103.pdf",
    "source_pages": [
      75,
      76
    ],
    "provenance_excerpt": "Mean, Median and Mode may be the same for some data.",
    "review_state": "approved",
    "qa_flags": []
  },
  {
    "question_id": "NCERT-EXEMPLAR-M7-CH3-Q40",
    "board": "NCERT",
    "class_level": 7,
    "subject": "Mathematics",
    "book": "Exemplar Problems - Mathematics",
    "chapter_number": 3,
    "chapter_title": "Data Handling",
    "language": "English",
    "source_kind": "EXEMPLAR",
    "question_type": "True/False",
    "question_text": "The probability of getting an ace out of a deck of cards is greater than 1.",
    "options": [
      "True",
      "False"
    ],
    "answer_key": "False",
    "answer_explanation": "Probability is never >1.",
    "difficulty": "easy",
    "blooms_level": "understand",
    "source_file": "gemp103.pdf",
    "source_pages": [
      75,
      76
    ],
    "provenance_excerpt": "The probability of getting an ace out of a deck of cards is greater than 1.",
    "review_state": "approved",
    "qa_flags": []
  },
  {
    "question_id": "NCERT-EXEMPLAR-M7-CH3-Q41",
    "board": "NCERT",
    "class_level": 7,
    "subject": "Mathematics",
    "book": "Exemplar Problems - Mathematics",
    "chapter_number": 3,
    "chapter_title": "Data Handling",
    "language": "English",
    "source_kind": "EXEMPLAR",
    "question_type": "True/False",
    "question_text": "Mean of the data is always from the given data.",
    "options": [
      "True",
      "False"
    ],
    "answer_key": "False",
    "answer_explanation": "Mean may not be one of the data points.",
    "difficulty": "easy",
    "blooms_level": "understand",
    "source_file": "gemp103.pdf",
    "source_pages": [
      75,
      76
    ],
    "provenance_excerpt": "Mean of the data is always from the given data.",
    "review_state": "approved",
    "qa_flags": []
  },
  {
    "question_id": "NCERT-EXEMPLAR-M7-CH3-Q42",
    "board": "NCERT",
    "class_level": 7,
    "subject": "Mathematics",
    "book": "Exemplar Problems - Mathematics",
    "chapter_number": 3,
    "chapter_title": "Data Handling",
    "language": "English",
    "source_kind": "EXEMPLAR",
    "question_type": "True/False",
    "question_text": "Median of the data may or may not be from the given data.",
    "options": [
      "True",
      "False"
    ],
    "answer_key": "True",
    "answer_explanation": "For even number of cases, it might be the mean of the two middle terms.",
    "difficulty": "easy",
    "blooms_level": "understand",
    "source_file": "gemp103.pdf",
    "source_pages": [
      75,
      76
    ],
    "provenance_excerpt": "Median of the data may or may not be from the given data.",
    "review_state": "approved",
    "qa_flags": []
  },
  {
    "question_id": "NCERT-EXEMPLAR-M7-CH3-Q43",
    "board": "NCERT",
    "class_level": 7,
    "subject": "Mathematics",
    "book": "Exemplar Problems - Mathematics",
    "chapter_number": 3,
    "chapter_title": "Data Handling",
    "language": "English",
    "source_kind": "EXEMPLAR",
    "question_type": "True/False",
    "question_text": "Mode of the data is always from the given data.",
    "options": [
      "True",
      "False"
    ],
    "answer_key": "True",
    "answer_explanation": "Mode is defined as the most frequent data point.",
    "difficulty": "easy",
    "blooms_level": "understand",
    "source_file": "gemp103.pdf",
    "source_pages": [
      75,
      76
    ],
    "provenance_excerpt": "Mode of the data is always from the given data.",
    "review_state": "approved",
    "qa_flags": []
  },
  {
    "question_id": "NCERT-EXEMPLAR-M7-CH3-Q44",
    "board": "NCERT",
    "class_level": 7,
    "subject": "Mathematics",
    "book": "Exemplar Problems - Mathematics",
    "chapter_number": 3,
    "chapter_title": "Data Handling",
    "language": "English",
    "source_kind": "EXEMPLAR",
    "question_type": "True/False",
    "question_text": "Mean of the observations can be lesser than each of the observations.",
    "options": [
      "True",
      "False"
    ],
    "answer_key": "False",
    "answer_explanation": "It cannot be lesser than the minimum.",
    "difficulty": "easy",
    "blooms_level": "understand",
    "source_file": "gemp103.pdf",
    "source_pages": [
      75,
      76
    ],
    "provenance_excerpt": "Mean of the observations can be lesser than each of the observations.",
    "review_state": "approved",
    "qa_flags": []
  },
  {
    "question_id": "NCERT-EXEMPLAR-M7-CH3-Q45",
    "board": "NCERT",
    "class_level": 7,
    "subject": "Mathematics",
    "book": "Exemplar Problems - Mathematics",
    "chapter_number": 3,
    "chapter_title": "Data Handling",
    "language": "English",
    "source_kind": "EXEMPLAR",
    "question_type": "True/False",
    "question_text": "Mean can never be a fraction.",
    "options": [
      "True",
      "False"
    ],
    "answer_key": "False",
    "answer_explanation": "Mean can be a fraction or decimal.",
    "difficulty": "easy",
    "blooms_level": "understand",
    "source_file": "gemp103.pdf",
    "source_pages": [
      75,
      76
    ],
    "provenance_excerpt": "Mean can never be a fraction.",
    "review_state": "approved",
    "qa_flags": []
  },
  {
    "question_id": "NCERT-EXEMPLAR-M7-CH3-Q46",
    "board": "NCERT",
    "class_level": 7,
    "subject": "Mathematics",
    "book": "Exemplar Problems - Mathematics",
    "chapter_number": 3,
    "chapter_title": "Data Handling",
    "language": "English",
    "source_kind": "EXEMPLAR",
    "question_type": "True/False",
    "question_text": "Range of the data is always from the data.",
    "options": [
      "True",
      "False"
    ],
    "answer_key": "False",
    "answer_explanation": "Highest - lowest might not be an element in the data.",
    "difficulty": "medium",
    "blooms_level": "understand",
    "source_file": "gemp103.pdf",
    "source_pages": [
      75,
      76
    ],
    "provenance_excerpt": "Range of the data is always from the data.",
    "review_state": "approved",
    "qa_flags": []
  },
  {
    "question_id": "NCERT-EXEMPLAR-M7-CH3-Q47",
    "board": "NCERT",
    "class_level": 7,
    "subject": "Mathematics",
    "book": "Exemplar Problems - Mathematics",
    "chapter_number": 3,
    "chapter_title": "Data Handling",
    "language": "English",
    "source_kind": "EXEMPLAR",
    "question_type": "True/False",
    "question_text": "The data 12, 13, 14, 15, 16 has every observation as mode.",
    "options": [
      "True",
      "False"
    ],
    "answer_key": "True",
    "answer_explanation": "Each occurs 1 time. So all are modes, or sometimes said 'no mode'. But technically true.",
    "difficulty": "medium",
    "blooms_level": "understand",
    "source_file": "gemp103.pdf",
    "source_pages": [
      75,
      76
    ],
    "provenance_excerpt": "The data 12, 13, 14, 15, 16 has every observation as mode.",
    "review_state": "approved",
    "qa_flags": []
  },
  {
    "question_id": "NCERT-EXEMPLAR-M7-CH3-Q48",
    "board": "NCERT",
    "class_level": 7,
    "subject": "Mathematics",
    "book": "Exemplar Problems - Mathematics",
    "chapter_number": 3,
    "chapter_title": "Data Handling",
    "language": "English",
    "source_kind": "EXEMPLAR",
    "question_type": "True/False",
    "question_text": "The range of the data 2, –5, 4, 3, 7, 6 would change if 2 was subtracted from each value in the data.",
    "options": [
      "True",
      "False"
    ],
    "answer_key": "False",
    "answer_explanation": "Range is invariant under uniform addition or subtraction.",
    "difficulty": "medium",
    "blooms_level": "understand",
    "source_file": "gemp103.pdf",
    "source_pages": [
      75,
      76
    ],
    "provenance_excerpt": "The range of the data 2, –5, 4, 3, 7, 6 would change if 2 was subtracted from each value in the data.",
    "review_state": "approved",
    "qa_flags": []
  },
  {
    "question_id": "NCERT-EXEMPLAR-M7-CH3-Q49",
    "board": "NCERT",
    "class_level": 7,
    "subject": "Mathematics",
    "book": "Exemplar Problems - Mathematics",
    "chapter_number": 3,
    "chapter_title": "Data Handling",
    "language": "English",
    "source_kind": "EXEMPLAR",
    "question_type": "True/False",
    "question_text": "The range of the data 3, 7, 1, –2, 2, 6, –3, –5 would change if 8 was added to each value in the data.",
    "options": [
      "True",
      "False"
    ],
    "answer_key": "False",
    "answer_explanation": "Range is unchanged.",
    "difficulty": "medium",
    "blooms_level": "understand",
    "source_file": "gemp103.pdf",
    "source_pages": [
      75,
      76
    ],
    "provenance_excerpt": "The range of the data 3, 7, 1, –2, 2, 6, –3, –5 would change if 8 was added to each value in the data.",
    "review_state": "approved",
    "qa_flags": []
  },
  {
    "question_id": "NCERT-EXEMPLAR-M7-CH3-Q50",
    "board": "NCERT",
    "class_level": 7,
    "subject": "Mathematics",
    "book": "Exemplar Problems - Mathematics",
    "chapter_number": 3,
    "chapter_title": "Data Handling",
    "language": "English",
    "source_kind": "EXEMPLAR",
    "question_type": "Short Answer",
    "question_text": "Calculate the Mean, Median and Mode of the following data: 5, 10, 10, 12, 13. Are these three equal?",
    "options": [],
    "answer_key": "Mean=10, Median=10, Mode=10. Yes.",
    "answer_explanation": "Sum = 50. Mean = 50/5 = 10. Middle term is 10. 10 appears most frequently.",
    "difficulty": "medium",
    "blooms_level": "apply",
    "source_file": "gemp103.pdf",
    "source_pages": [
      76,
      77
    ],
    "provenance_excerpt": "Calculate the Mean, Median and Mode of the following data: 5, 10, 10, 12, 13. Are these three equal?",
    "review_state": "approved",
    "qa_flags": []
  },
  {
    "question_id": "NCERT-EXEMPLAR-M7-CH3-Q51",
    "board": "NCERT",
    "class_level": 7,
    "subject": "Mathematics",
    "book": "Exemplar Problems - Mathematics",
    "chapter_number": 3,
    "chapter_title": "Data Handling",
    "language": "English",
    "source_kind": "EXEMPLAR",
    "question_type": "Short Answer",
    "question_text": "Find the mean of the first ten even natural numbers.",
    "options": [],
    "answer_key": "11",
    "answer_explanation": "First ten even: 2, 4, 6, 8, 10, 12, 14, 16, 18, 20. Sum = 110. Mean = 11.",
    "difficulty": "medium",
    "blooms_level": "apply",
    "source_file": "gemp103.pdf",
    "source_pages": [
      76,
      77
    ],
    "provenance_excerpt": "Find the mean of the first ten even natural numbers.",
    "review_state": "approved",
    "qa_flags": []
  },
  {
    "question_id": "NCERT-EXEMPLAR-M7-CH3-Q57",
    "board": "NCERT",
    "class_level": 7,
    "subject": "Mathematics",
    "book": "Exemplar Problems - Mathematics",
    "chapter_number": 3,
    "chapter_title": "Data Handling",
    "language": "English",
    "source_kind": "EXEMPLAR",
    "question_type": "Short Answer",
    "question_text": "Calculate the mean of its median and mode for the data: 6, 2, 5, 4, 3, 4, 4, 2, 3",
    "options": [],
    "answer_key": "4",
    "answer_explanation": "Ordered: 2, 2, 3, 3, 4, 4, 4, 5, 6. Median = 4. Mode = 4. Mean of 4 and 4 is 4.",
    "difficulty": "hard",
    "blooms_level": "apply",
    "source_file": "gemp103.pdf",
    "source_pages": [
      76,
      77
    ],
    "provenance_excerpt": "Calculate the mean of its median and mode for the data: 6, 2, 5, 4, 3, 4, 4, 2, 3",
    "review_state": "approved",
    "qa_flags": []
  },
  {
    "question_id": "NCERT-EXEMPLAR-M7-CH3-Q58",
    "board": "NCERT",
    "class_level": 7,
    "subject": "Mathematics",
    "book": "Exemplar Problems - Mathematics",
    "chapter_number": 3,
    "chapter_title": "Data Handling",
    "language": "English",
    "source_kind": "EXEMPLAR",
    "question_type": "Short Answer",
    "question_text": "Find the median of the given data if the mean is 4.5. 5, 7, 7, 8, x, 5, 4, 3, 1, 2",
    "options": [],
    "answer_key": "5",
    "answer_explanation": "Sum = 42 + x. (42+x)/10 = 4.5 => x = 3. Ordered: 1, 2, 3, 3, 4, 5, 5, 7, 7, 8. Median = (4+5)/2 = 4.5.",
    "difficulty": "hard",
    "blooms_level": "apply",
    "source_file": "gemp103.pdf",
    "source_pages": [
      76,
      77
    ],
    "provenance_excerpt": "Find the median of the given data if the mean is 4.5. 5, 7, 7, 8, x, 5, 4, 3, 1, 2",
    "review_state": "approved",
    "qa_flags": []
  },
  {
    "question_id": "NCERT-EXEMPLAR-M7-CH3-Q59",
    "board": "NCERT",
    "class_level": 7,
    "subject": "Mathematics",
    "book": "Exemplar Problems - Mathematics",
    "chapter_number": 3,
    "chapter_title": "Data Handling",
    "language": "English",
    "source_kind": "EXEMPLAR",
    "question_type": "Short Answer",
    "question_text": "What is the probability of the sun setting tomorrow?",
    "options": [],
    "answer_key": "1",
    "answer_explanation": "It is a certain event.",
    "difficulty": "easy",
    "blooms_level": "apply",
    "source_file": "gemp103.pdf",
    "source_pages": [
      76,
      77
    ],
    "provenance_excerpt": "What is the probability of the sun setting tomorrow?",
    "review_state": "approved",
    "qa_flags": []
  },
  {
    "question_id": "NCERT-EXEMPLAR-M7-CH3-Q61",
    "board": "NCERT",
    "class_level": 7,
    "subject": "Mathematics",
    "book": "Exemplar Problems - Mathematics",
    "chapter_number": 3,
    "chapter_title": "Data Handling",
    "language": "English",
    "source_kind": "EXEMPLAR",
    "question_type": "Short Answer",
    "question_text": "What is the probability that a student chosen at random out of 3 girls and 4 boys is a boy?",
    "options": [],
    "answer_key": "4/7",
    "answer_explanation": "Total = 7. Boys = 4. Prob = 4/7.",
    "difficulty": "easy",
    "blooms_level": "apply",
    "source_file": "gemp103.pdf",
    "source_pages": [
      76,
      77
    ],
    "provenance_excerpt": "What is the probability that a student chosen at random out of 3 girls and 4 boys is a boy?",
    "review_state": "approved",
    "qa_flags": []
  },
  {
    "question_id": "NCERT-EXEMPLAR-M7-CH3-Q65",
    "board": "NCERT",
    "class_level": 7,
    "subject": "Mathematics",
    "book": "Exemplar Problems - Mathematics",
    "chapter_number": 3,
    "chapter_title": "Data Handling",
    "language": "English",
    "source_kind": "EXEMPLAR",
    "question_type": "Short Answer",
    "question_text": "Find the mean of first six multiples of 4.",
    "options": [],
    "answer_key": "14",
    "answer_explanation": "Multiples: 4, 8, 12, 16, 20, 24. Sum = 84. Mean = 84/6 = 14.",
    "difficulty": "medium",
    "blooms_level": "apply",
    "source_file": "gemp103.pdf",
    "source_pages": [
      76,
      77
    ],
    "provenance_excerpt": "Find the mean of first six multiples of 4.",
    "review_state": "approved",
    "qa_flags": []
  },
  {
    "question_id": "NCERT-EXEMPLAR-M7-CH3-Q67",
    "board": "NCERT",
    "class_level": 7,
    "subject": "Mathematics",
    "book": "Exemplar Problems - Mathematics",
    "chapter_number": 3,
    "chapter_title": "Data Handling",
    "language": "English",
    "source_kind": "EXEMPLAR",
    "question_type": "Short Answer",
    "question_text": "The mean of three numbers is 10. The mean of other four numbers is 12. Find the mean of all the numbers.",
    "options": [],
    "answer_key": "78/7 or 11.14",
    "answer_explanation": "Sum1 = 30, Sum2 = 48. Total sum = 78. Mean = 78/7.",
    "difficulty": "medium",
    "blooms_level": "apply",
    "source_file": "gemp103.pdf",
    "source_pages": [
      76,
      77
    ],
    "provenance_excerpt": "The mean of three numbers is 10. The mean of other four numbers is 12. Find the mean of all the numbers.",
    "review_state": "approved",
    "qa_flags": []
  }
]