[
  {
    "question_id": "NCERT-EXEMPLAR-M9-CH3-Q1",
    "board": "NCERT",
    "class_level": 9,
    "subject": "Mathematics",
    "book": "Exemplar Problems - Mathematics",
    "chapter_number": 3,
    "chapter_title": "Coordinate Geometry",
    "language": "English",
    "source_kind": "EXEMPLAR",
    "question_type": "SHORT_ANSWER",
    "question_text": "Write whether the following statements are True or False? Justify your answer. (i) Point (3, 0) lies in the first quadrant. (ii) Points (1, \u20131) and (\u20131, 1) lie in the same quadrant. 1 (iii) The coordinates of a point whose ordinate is \u2212 and abscissa is 1 are 2 1 \u2212 ,1 . 2 (iv) A point lies on y-axis at a distance of 2 units from the x-axis. Its coordinates are (2, 0). (v) (\u20131, 7) is a point in the II quadrant.",
    "options": [],
    "answer_key": "",
    "answer_explanation": "",
    "difficulty": "medium",
    "blooms_level": "understand",
    "source_file": "ieep203.pdf",
    "source_pages": [],
    "image_required": false,
    "figure_ref": [],
    "provenance_excerpt": "Write whether the following statements are True or False? Justify your answer. (i) Point (3, 0) lies in the first quadrant. (ii) Points (1, \u20131) and (\u2013",
    "review_state": "approved",
    "qa_flags": [],
    "is_example": false
  }
]
