{
  "provenance": {
    "board": "NCERT",
    "class": "6",
    "subject": "Science",
    "book": "Curiosity",
    "chapterNumber": 8,
    "chapterTitle": "A Journey Through States of Matter",
    "sourceFile": "fecu108.pdf"
  },
  "questions": [
    {
      "sourceKind": "CANONICAL",
      "section": "Exercise",
      "pageNumber": 102,
      "text": "Which state of matter has a fixed shape and volume?",
      "type": "MCQ",
      "options": ["Solid", "Liquid", "Gas", "Plasma"],
      "correctAnswer": "Solid",
      "explanation": "Solids have both fixed shape and fixed volume. The particles are tightly packed and cannot move freely."
    },
    {
      "sourceKind": "CANONICAL",
      "section": "Exercise",
      "pageNumber": 103,
      "text": "Water changes from liquid to gas through evaporation.",
      "type": "TRUE_FALSE",
      "options": ["True", "False"],
      "correctAnswer": "True",
      "explanation": "Evaporation is the process where liquid water changes into water vapor (gas) when heated."
    },
    {
      "sourceKind": "CANONICAL",
      "section": "In-text",
      "pageNumber": 98,
      "text": "What happens to ice when it is heated?",
      "type": "SHORT_ANSWER",
      "correctAnswer": "Ice melts and changes from solid to liquid (water).",
      "explanation": "When ice (solid water) is heated, it absorbs energy and melts into liquid water at 0°C."
    },
    {
      "sourceKind": "CANONICAL",
      "section": "Exercise",
      "pageNumber": 104,
      "text": "The process of changing from gas to liquid is called ________.",
      "type": "FILL_IN_BLANKS",
      "correctAnswer": "condensation",
      "explanation": "Condensation is the process where water vapor (gas) cools and changes back into liquid water."
    }
  ]
}
