[
  {
    "sourceKind": "DERIVED",
    "reviewStatus": "DRAFT",
    "generationRunId": "class7-english-offline-gen",
    "subjectId": "English",
    "chapter": "Chapter 1: The Magic of Poetry",
    "derivedFromChapterId": "Chapter 1: The Magic of Poetry",
    "generationRationale": "Shifted to identifying a structural element of poetry using a definition application context.",
    "sourceCanonicalQuestionIds": ["69c778a36bfcc2d1f3968eb1"],
    "type": "MCQ",
    "text": "If a poet groups four lines together to form a unit within a poem, what is this unit called?",
    "options": ["Paragraph", "Stanza", "Sentence", "Syllable"],
    "correctAnswer": "Stanza",
    "explanation": "In poetry, a stanza is a grouped set of lines, functioning similarly to a paragraph in prose.",
    "points": 1,
    "provenance": { "board": "NCERT", "class": "7", "subject": "English", "book": "English Echoes", "chapterNumber": 1, "chapterTitle": "The Magic of Poetry", "sourceFile": "gepr101.pdf", "extraction_run_id": "7-English-english-echoes-ch1-v1" }
  },
  {
    "sourceKind": "DERIVED",
    "reviewStatus": "DRAFT",
    "generationRunId": "class7-english-offline-gen",
    "subjectId": "English",
    "chapter": "Chapter 1: The Magic of Poetry",
    "derivedFromChapterId": "Chapter 1: The Magic of Poetry",
    "generationRationale": "Tests the concept of personification by asking the student to identify an example of it.",
    "sourceCanonicalQuestionIds": ["69c778a36bfcc2d1f3968eb0"],
    "type": "TRUE_FALSE",
    "text": "The phrase 'The wind whispered secrets through the trees' is an example of personification.",
    "options": ["True", "False"],
    "correctAnswer": "True",
    "explanation": "Personification is giving human qualities to non-human things. Whispering is a human action, here attributed to the wind.",
    "points": 1,
    "provenance": { "board": "NCERT", "class": "7", "subject": "English", "book": "English Echoes", "chapterNumber": 1, "chapterTitle": "The Magic of Poetry", "sourceFile": "gepr101.pdf", "extraction_run_id": "7-English-english-echoes-ch1-v1" }
  },
  {
    "sourceKind": "DERIVED",
    "reviewStatus": "DRAFT",
    "generationRunId": "class7-english-offline-gen",
    "subjectId": "English",
    "chapter": "Chapter 2: The Bear Story",
    "derivedFromChapterId": "Chapter 2: The Bear Story",
    "generationRationale": "Shifted focus to testing recall of the bear's living conditions.",
    "sourceCanonicalQuestionIds": ["69c78505ba91199906572ce7"],
    "type": "FILL_IN_BLANKS",
    "text": "Unlike a wild animal kept in captivity, the bear in the story was not tied with a ________ all the time.",
    "correctAnswer": "chain",
    "explanation": "The story emphasizes that the bear was mostly free and friendly, and not chained constantly.",
    "points": 1,
    "provenance": { "board": "NCERT", "class": "7", "subject": "English", "book": "English Echoes", "chapterNumber": 2, "chapterTitle": "The Bear Story", "sourceFile": "gepr102.pdf", "extraction_run_id": "7-English-english-echoes-ch2-v1" }
  },
  {
    "sourceKind": "DERIVED",
    "reviewStatus": "DRAFT",
    "generationRunId": "class7-english-offline-gen",
    "subjectId": "English",
    "chapter": "Chapter 2: The Bear Story",
    "derivedFromChapterId": "Chapter 2: The Bear Story",
    "generationRationale": "Tests narrative comprehension by combining multiple traits.",
    "sourceCanonicalQuestionIds": ["69c78505ba91199906572ce8", "69c78505ba91199906572ce9"],
    "type": "SHORT_ANSWER",
    "text": "Based on its behavior and diet, how would you describe the bear's relationship with humans?",
    "correctAnswer": "The bear was friendly, affectionate (licking and playing), and accustomed to human food like bread.",
    "explanation": "The bear displayed domesticated, affectionate behaviors rather than wild, aggressive ones.",
    "points": 2,
    "provenance": { "board": "NCERT", "class": "7", "subject": "English", "book": "English Echoes", "chapterNumber": 2, "chapterTitle": "The Bear Story", "sourceFile": "gepr102.pdf", "extraction_run_id": "7-English-english-echoes-ch2-v1" }
  },
  {
    "sourceKind": "DERIVED",
    "reviewStatus": "DRAFT",
    "generationRunId": "class7-english-offline-gen",
    "subjectId": "English", "chapter": "Chapter 3: The Desert",
    "derivedFromChapterId": "Chapter 3: The Desert",
    "generationRationale": "Applied the concept of an oasis to a descriptive scenario.",
    "sourceCanonicalQuestionIds": ["69c7a8dbcf7ab372feadd3e1"],
    "type": "MCQ",
    "text": "If travelers in a vast, dry landscape stumble upon a green area with a natural spring of water, they have found an:",
    "options": ["Island", "Oasis", "Estuary", "Isthmus"],
    "correctAnswer": "Oasis",
    "explanation": "An oasis is a fertile spot in a desert where water is found, allowing plants to grow.",
    "points": 1,
    "provenance": { "board": "NCERT", "class": "7", "subject": "English", "book": "English Echoes", "chapterNumber": 3, "chapterTitle": "The Desert", "sourceFile": "gepr103.pdf", "extraction_run_id": "7-English-english-echoes-ch3-v1" }
  },
  {
    "sourceKind": "DERIVED",
    "reviewStatus": "DRAFT",
    "generationRunId": "class7-english-offline-gen",
    "subjectId": "English", "chapter": "Chapter 3: The Desert",
    "derivedFromChapterId": "Chapter 3: The Desert",
    "generationRationale": "Shifted to testing understanding of a specific biological adaptation.",
    "sourceCanonicalQuestionIds": ["69c7a8dbcf7ab372feadd3e2"],
    "type": "TRUE_FALSE",
    "text": "The primary function of a camel's hump is to store large quantities of liquid water for long journeys.",
    "options": ["True", "False"],
    "correctAnswer": "False",
    "explanation": "Camels store fat, not water, in their humps. This fat can be broken down to provide energy when food is scarce.",
    "points": 1,
    "provenance": { "board": "NCERT", "class": "7", "subject": "English", "book": "English Echoes", "chapterNumber": 3, "chapterTitle": "The Desert", "sourceFile": "gepr103.pdf", "extraction_run_id": "7-English-english-echoes-ch3-v1" }
  }
]